{"9907.jpg34737": {"size": 34737, "regions": {"0": {"region_attributes": {"animal": "cat"}, "shape_attributes": {"y": 1, "name": "rect", "height": 286, "x": 158, "width": 278}}}, "file_attributes": {}, "fileref": "", "base64_img_data": "", "filename": "9907.jpg"}, "9899.jpg18179": {"size": 18179, "regions": {}, "file_attributes": {}, "fileref": "", "base64_img_data": "", "filename": "9899.jpg"}, "9875.jpg13430": {"size": 13430, "regions": {}, "file_attributes": {}, "fileref": "", "base64_img_data": "", "filename": "9875.jpg"}, "9891.jpg27119": {"size": 27119, "regions": {}, "file_attributes": {}, "fileref": "", "base64_img_data": "", "filename": "9891.jpg"}, "9852.jpg23580": {"size": 23580, "regions": {}, "file_attributes": {}, "fileref": "", "base64_img_data": "", "filename": "9852.jpg"}, "9838.jpg30716": {"size": 30716, "regions": {}, "file_attributes": {}, "fileref": "", "base64_img_data": "", "filename": "9838.jpg"}, "9867.jpg26132": {"size": 26132, "regions": {"0": {"region_attributes": {"animal": "cat"}, "shape_attributes": {"y": 54, "name": "rect", "height": 190, "x": 114, "width": 214}}}, "file_attributes": {}, "fileref": "", "base64_img_data": "", "filename": "9867.jpg"}, "9829.jpg94404": {"size": 94404, "regions": {}, "file_attributes": {}, "fileref": "", "base64_img_data": "", "filename": "9829.jpg"}, "9827.jpg23269": {"size": 23269, "regions": {}, "file_attributes": {}, "fileref": "", "base64_img_data": "", "filename": "9827.jpg"}, "9860.jpg66911": {"size": 66911, "regions": {}, "file_attributes": {}, "fileref": "", "base64_img_data": "", "filename": "9860.jpg"}, "9858.jpg20712": {"size": 20712, "regions": {}, "file_attributes": {}, "fileref": "", "base64_img_data": "", "filename": "9858.jpg"}, "9883.jpg20884": {"size": 20884, "regions": {"0": {"region_attributes": {"animal": "cat"}, "shape_attributes": {"y": 25, "name": "rect", "height": 182, "x": 253, "width": 183}}}, "file_attributes": {}, "fileref": "", "base64_img_data": "", "filename": "9883.jpg"}}